spamdetector/README.md
spamdetector/__init__.py
spamdetector/models/spam_detector_logit_model.pkl
spamdetector/models/spam_detector_nb_model.pkl
spamdetector/models/spam_detector_rf_model.pkl
spamdetector/models/spam_vectorizer.pkl
spamdetector/spamdetector.py
spamdetector-0.1.2.dist-info/WHEEL
spamdetector-0.1.2.dist-info/METADATA
spamdetector-0.1.2.dist-info/RECORD
